whatsapp_message_vonage_local/__init__.py
whatsapp_message_vonage_local/vonage_whatsapp_message_local.py
whatsapp_message_vonage_local-0.0.24.dist-info/METADATA
whatsapp_message_vonage_local-0.0.24.dist-info/WHEEL
whatsapp_message_vonage_local-0.0.24.dist-info/top_level.txt
whatsapp_message_vonage_local-0.0.24.dist-info/RECORD
