Metadata-Version: 2.1
Name: whatsapp-message-vonage-local
Version: 0.0.24
Summary: PyPI Package for Circles whatsapp-message-vonage-local
Home-page: https://github.com/circles-zone/whatsapp-message-vonage-local-python-package
Author: Circles
Author-email: info@circles.life
Classifier: Programming Language :: Python :: 3
Classifier: License :: Other/Proprietary License
Classifier: Operating System :: OS Independent
Requires-Dist: vonage >=3.11.0
Requires-Dist: message-local >=0.0.123
Requires-Dist: logger-local >=0.0.135
Requires-Dist: database-mysql-local >=0.0.290
Requires-Dist: api-management-local >=0.0.61
Requires-Dist: python-sdk-remote >=0.0.93
